matviz/__init__.py
matviz/_version.py
matviz/cbrt_scale.py
matviz/circle_utils.py
matviz/datetime_converter.py
matviz/doctools.py
matviz/etl.py
matviz/helpers_graphing.py
matviz/histogram_utils.py
matviz/viz.py
matviz-0.2.4.dist-info/licenses/LICENSE
matviz-0.2.4.dist-info/METADATA
matviz-0.2.4.dist-info/WHEEL
matviz-0.2.4.dist-info/top_level.txt
matviz-0.2.4.dist-info/RECORD
