Metadata-Version: 2.4
Name: matviz
Version: 0.2.4
Summary: matviz: matrix data visualization
Author-email: Jonathan Lansey <jonathan@lansey.net>
Maintainer-email: Jonathan Lansey <jonathan@lansey.net>
License: BSD-3-Clause
Project-URL: Homepage, https://github.com/JLansey/matviz
Project-URL: Repository, https://github.com/JLansey/matviz
Project-URL: Documentation, https://github.com/JLansey/matviz
Classifier: Intended Audience :: Science/Research
Classifier: Programming Language :: Python :: 3.10
Classifier: Programming Language :: Python :: 3.11
Classifier: Programming Language :: Python :: 3.12
Classifier: Topic :: Scientific/Engineering :: Visualization
Classifier: License :: OSI Approved :: BSD License
Requires-Python: >=3.10
License-File: LICENSE
Requires-Dist: numpy>=1.20.0
Requires-Dist: scipy>=1.7.0
Requires-Dist: pandas>=1.3.0
Requires-Dist: matplotlib>=3.4.0
Requires-Dist: seaborn>=0.11.0
Requires-Dist: scikit-learn>=0.24.0
Requires-Dist: python-dateutil>=2.8.0
Requires-Dist: pyyaml>=5.1
Requires-Dist: pytz
Provides-Extra: dev
Requires-Dist: pytest>=7.0.0; extra == "dev"
Requires-Dist: pytest-cov>=4.0.0; extra == "dev"
Requires-Dist: flake8>=5.0.0; extra == "dev"
Requires-Dist: nbval>=0.10.0; extra == "dev"
Requires-Dist: pytest-mpl>=0.16.0; extra == "dev"
Provides-Extra: docs
Requires-Dist: sphinx>=5.0.0; extra == "docs"
Requires-Dist: sphinx-rtd-theme>=1.0.0; extra == "docs"
Provides-Extra: notebook
Requires-Dist: mpld3>=0.5.0; extra == "notebook"
Provides-Extra: all
Requires-Dist: matviz[dev,docs,notebook]; extra == "all"
Dynamic: license-file
